pyhid_usb_relay/__init__.py
pyhid_usb_relay/__main__.py
pyhid_usb_relay/controller.py
pyhid_usb_relay/exceptions.py
pyhid_usb_relay/find.py
pyhid_usb_relay/main.py
pyhid_usb_relay/version.py
pyhid_usb_relay-1.2.0.dist-info/METADATA
pyhid_usb_relay-1.2.0.dist-info/WHEEL
pyhid_usb_relay-1.2.0.dist-info/entry_points.txt
pyhid_usb_relay-1.2.0.dist-info/licenses/COPYING
pyhid_usb_relay-1.2.0.dist-info/RECORD
