Metadata-Version: 2.3
Name: pyhid-usb-relay
Version: 1.2.0
Summary: A tool for controlling USB HID relays
Project-URL: Homepage, https://github.com/JPEWdev/pyhid-usb-relay
Project-URL: Repository, https://github.com/JPEWdev/pyhid-usb-relay.git
Project-URL: Issues, https://github.com/JPEWdev/pyhid-usb-relay/issues
Author-email: Joshua Watt <JPEWhacker@gmail.com>
Maintainer-email: Joshua Watt <JPEWhacker@gmail.com>
License: Copyright 2020 Joshua Watt <JPEWhacker@gmail.com>
License-File: COPYING
Classifier: License :: OSI Approved :: MIT License
Classifier: Operating System :: OS Independent
Classifier: Programming Language :: Python :: 3
Classifier: Programming Language :: Python :: 3.8
Classifier: Programming Language :: Python :: 3.9
Classifier: Programming Language :: Python :: 3.10
Classifier: Programming Language :: Python :: 3.11
Classifier: Programming Language :: Python :: 3.12
Requires-Dist: libusb>=1.0.26b5; sys_platform == 'win32'
Requires-Dist: pyusb>=1.2.1
Requires-Dist: pyyaml>=6.0
Requires-Dist: xdg>=5.1.1
Provides-Extra: dev
Requires-Dist: black; extra == 'dev'
Requires-Dist: flake8; extra == 'dev'
Requires-Dist: pytest>=7.4; extra == 'dev'
